{
    "FileName": "hl_490_16EEC6AC.cndy",
    "Number of Strings": "71",
    "Size (bytes)": "852",
    "Address": "0x77C",
    "Strings": [
        "ホゥ？！",
        "ホー！ホ？",
        "ホウーン！",
        "ホー！",
        "ホエエ‥‥",
        "ギャギャ？！",
        "ギャ‥オ？",
        "ギャォ！",
        "ギャイナラ！",
        "ギャーーーオゥ！",
        "ギャア‥‥",
        "キャォ？！",
        "キャーオ‥？？",
        "キィヤアア！",
        "キャオーン！",
        "キャーオ！",
        "キャア！",
        "いくぞクエスター！",
        "おらァッ！ ちっ。",
        "グばぁ！",
        "くらえ！！",
        "おらァッ！",
        "シッ？！",
        "シッ‥ シ？",
        "シシッ‥‥",
        "フシッ！",
        "シャシャシャ‥‥",
        "シッシッ！",
        "シィッ！",
        "シャッ？！",
        "シャーッ！",
        "シャシャッ！",
        "シャハーーーーッ！",
        "ショエェ‥‥",
        "シャグルルル！！",
        "シャアッ！",
        "シャッシャッ！！",
        "シャガーーーーッ！",
        "いくぜ！",
        "フッ‥ おっ",
        "トゥッ！",
        "フッフッ！",
        "オラオラァーーーッ！",
        "オゥリャアッ！",
        "フッ！",
        "シャッ！",
        "シャウ！シャオ！シャハァーーッ！",
        "ショウッ！",
        "‥‥‥",
        "オオォ‥‥",
        "だいかいてんぎり！",
        "ウー‥‥",
        "タチサレ‥‥",
        "メッセヨ‥‥",
        "ヒャ！？",
        "ヒヒ‥‥",
        "ヒャ‥ ヒェ？",
        "フヒッ",
        "ヒャッ！",
        "クヒ‥‥",
        "フヒ‥‥",
        "ゆくぞ！",
        "かッ‥ こしゃくな‥‥",
        "かッ！",
        "む‥‥",
        "いかん‥‥",
        "はッ",
        "ボゲ？！",
        "ボギャボゲ？",
        "ボギャッ！",
        "ボゲェ‥‥"
    ]
}