{
    "FileName": "hl_582_1ACE9F14.cndy",
    "Number of Strings": "26",
    "Size (bytes)": "300",
    "Address": "0x240",
    "Strings": [
        "‥‥‥‥。",
        "ちからを ためている",
        "くらえ！",
        "ハァアアアア‥‥‥",
        "ばかめ！",
        "むん！",
        "？！",
        "ヒュ〜‥？",
        "ヒュ〜‥‥",
        "ヒェ〜‥‥",
        "いくぞクエスター！",
        "ぬんッ‥ ちっ！",
        "ぬんッ！",
        "おろかな‥‥",
        "ちっ‥‥",
        "はッ！",
        "ぬン！",
        "‥‥‥",
        "‥‥",
        "‥‥！",
        "巨神盾付き",
        "巨神",
        "おばけ",
        "1st魔導士(地下道)",
        "1st魔導士(砂漠の遺跡)",
        "ナナシ(2nd：フード男)"
    ]
}