{
    "FileName": "hl_578_1A9ABFE0.cndy",
    "Number of Strings": "69",
    "Size (bytes)": "880",
    "Address": "0x26C",
    "Strings": [
        "キャォ？！",
        "キャーオ‥？？",
        "キィヤアア！",
        "キャオーン！",
        "キャーオ！",
        "キャア！",
        "いくぞクエスター！",
        "おらァッ！ ちっ。",
        "グばぁ！",
        "くらえ！！",
        "おらァッ！",
        "ララッ？",
        "トォ‥アラッ？",
        "リルレロ〜",
        "ギャッ！",
        "ワーワーーー！",
        "ヘルプミー！！",
        "ノーノー！",
        "トォッ！",
        "いくぞ！",
        "アチョ？",
        "ハイヤ！",
        "むむっ‥‥",
        "ホゥワ！",
        "アイヤー！",
        "かいてんビンタ！",
        "ぷーーッ！",
        "スミを まきちらした",
        "アホー！",
        "アチョー！",
        "ギッ！",
        "ギー？",
        "ギギー！",
        "ギッギッギッ‥‥",
        "ギー！",
        "いくぜ！",
        "ハァッ‥ ちっ",
        "ダッ！",
        "フンッ！",
        "ハァッ！",
        "オラァッ！",
        "おっ！",
        "たあッ‥ おっ？",
        "たあッ！",
        "あ！",
        "やっ‥ あれ？",
        "やっ！",
        "獲物グリーン",
        "獲物アイス",
        "獲物",
        "獲物：2ndオラゴン(岩山ボス)",
        "獲物縞(青黄)",
        "獲物縞(緑赤)",
        "獲物縞(赤黒)",
        "獲物アイス(陣取ボス)",
        "道化触角",
        "道化出目",
        "道化マロン",
        "道化牛角",
        "道化ピエロ",
        "道化出目(陣取ボス)",
        "イカキング団",
        "バクラ一味",
        "イカキング(イカッチ篇のボス)",
        "ショイカー(イカキングの部下)",
        "バクラ:  2nd盗賊団ボス",
        "ホッパー:2nd盗賊団側近",
        "ギャロ:  2nd盗賊団側近",
        "３人いっぺんに置く"
    ]
}